pycoreapi/__init__.py
pycoreapi/connection.py
pycoreapi/core.py
pycoreapi/exceptions.py
pycoreapi/request.py
pycoreapi/response.py
pycoreapi/utils.py
pycoreapi/validators.py
pycoreapi-0.2.1.dist-info/LICENSE
pycoreapi-0.2.1.dist-info/METADATA
pycoreapi-0.2.1.dist-info/WHEEL
pycoreapi-0.2.1.dist-info/top_level.txt
pycoreapi-0.2.1.dist-info/RECORD
